{
    "diaryId":  "1191",
    "parserVersion":  "2026.04.01.11",
    "analyzedAt":  "2026-04-01T15:55:49",
    "sourcePdfUrl":  "https://www.iguape.sp.gov.br/uploads/diario_oficial_edicao_1047-_28071521.pdf",
    "sourceLocalPdfRelative":  "storage/pdfs/2025/diario_oficial_edicao_1047-_28071521.pdf",
    "keywords":  [
                     "aditivo",
                     "contrato",
                     "dispensa",
                     "homologacao",
                     "inexigibilidade"
                 ],
    "analysisReason":  [
                           "keyword_map"
                       ],
    "summary":  {
                    "pageCount":  0,
                    "relevantPageCount":  0,
                    "blockCount":  0,
                    "itemCount":  0,
                    "totalValue":  "R$ 0,00",
                    "error":  "Não é possível associar o argumento ao parâmetro \u0027Text\u0027 porque ele é uma cadeia de caracteres vazia."
                },
    "items":  [

              ]
}
