{
    "diaryId":  "310",
    "parserVersion":  "2026.03.18.10",
    "analyzedAt":  "2026-03-18T17:16:44",
    "sourcePdfUrl":  "https://www.iguape.sp.gov.br/uploads/daa93622a7337fd3e6998b4f1e2ab5eb.pdf",
    "sourceLocalPdfRelative":  "storage/pdfs/2022/daa93622a7337fd3e6998b4f1e2ab5eb.pdf",
    "keywords":  [
                     "contrato",
                     "dispensa",
                     "homologacao"
                 ],
    "summary":  {
                    "pageCount":  2,
                    "itemCount":  1,
                    "totalValue":  "R$ 0,00"
                },
    "items":  [
                  {
                      "type":  "Aviso de Licitacao",
                      "actTitle":  "AVISO DE LICITACAO - PREGAO PRESENCIAL",
                      "recordClass":  "licitacao_ou_contratacao",
                      "recordClassLabel":  "Licitacao e contratacao",
                      "confidenceScore":  8,
                      "confidenceLabel":  "media",
                      "pageNumber":  1,
                      "contractNumber":  "",
                      "processNumber":  "035/2021",
                      "modality":  "PREGAO PRESENCIAL nº. 035/2021",
                      "contractor":  "",
                      "cnpj":  "",
                      "object":  "REGISTRO DE PRECOS PELO PERIODO DE 12 (DOZE) MESES VISANDO CONTRATACOES FUTURAS PARA CONFECCAO DE MATERIAIS GRAFICOS, DIVULGACAO E IMPRESSAO, PARA ATENDER DIVERSAS SECRETARIAS E DEPARTAMENTOS DA PREFEITURA MUNICIPAL DE IGUAPE/SP. LEGISLACAO: Lei Federal n.º 8.666/93, de 21 de junho de 1993, Lei Federal n.º 10.520 de 17 de julho de 2002, Decreto nº 7.892 de 23/01/2013, Lei Complementar n.º 123 de 14 de dezembro de 2006 e Lei Complementar n.º 147 de 07 de agosto de 2014",
                      "value":  "",
                      "term":  "",
                      "signatureDate":  "PARA A ENTREGA DO(S) DOCUMENTO(S) PARA CREDENCIAMENTO, DA DECLARACAO DE QUE A",
                      "legalBasis":  "",
                      "primaryOrganizationId":  "municipal-gestao-planejamento",
                      "primaryOrganizationName":  "Secretaria de Gestao e Planejamento",
                      "primaryOrganizationSphere":  "municipal",
                      "primaryOrganizationAreaId":  "gestao-planejamento",
                      "mentionedOrganizationIds":  [
                                                       "municipal-prefeitura",
                                                       "municipal-gestao-planejamento"
                                                   ],
                      "mentionedOrganizationNames":  [
                                                         "Prefeitura Municipal de Iguape",
                                                         "Secretaria de Gestao e Planejamento"
                                                     ],
                      "excerpt":  "AVISO DE LICITACAO\n PREGAO PRESENCIAL\n\nEncontra-se aberto na Prefeitura Municipal de Iguape, situada na Avenida Adhemar de Barros, n.º 1.070, Bairro Porto do\nRibeira, Iguape/SP, CEP 11.920-000, o PREGAO PRESENCIAL nº. 035/2021, do tipo MENOR PRECO GLOBAL POR\nLOTE, conforme especificacoes detalhadas no Edital.\nOBJETO: REGISTRO DE PRECOS PELO PERIODO DE 12 (DOZE) MESES VISANDO CONTRATACOES FUTURAS\nPARA CONFECCAO DE MATERIAIS GRAFICOS, DIVULGACAO E IMPRESSAO, PARA ATENDER DIVERSAS\nSECRETARIAS E DEPARTAMENTOS DA PREFEI",
                      "completeness":  "media",
                      "flags":  [

                                ]
                  }
              ]
}
