{
    "diaryId":  "570",
    "parserVersion":  "2026.04.01.11",
    "analyzedAt":  "2026-04-01T15:58:48",
    "sourcePdfUrl":  "https://www.iguape.sp.gov.br/uploads/0f7c9f367f9f95d93b3c4246cef13ae5.pdf",
    "sourceLocalPdfRelative":  "storage/pdfs/2023/0f7c9f367f9f95d93b3c4246cef13ae5.pdf",
    "keywords":  [
                     "contrato",
                     "dispensa"
                 ],
    "analysisReason":  [
                           "keyword_map"
                       ],
    "summary":  {
                    "pageCount":  6,
                    "relevantPageCount":  1,
                    "blockCount":  2,
                    "itemCount":  2,
                    "totalValue":  "R$ 0,00"
                },
    "items":  [
                  {
                      "type":  "Aviso de Licitacao",
                      "actTitle":  "AVISO DE LICITACAO - PREGAO PRESENCIAL",
                      "recordClass":  "licitacao_ou_contratacao",
                      "recordClassLabel":  "Licitacao e contratacao",
                      "confidenceScore":  9,
                      "confidenceLabel":  "alta",
                      "pageNumber":  4,
                      "contractNumber":  "",
                      "processNumber":  "034/2023",
                      "modality":  "PREGAO PRESENCIAL nº. 034/2023",
                      "contractor":  "",
                      "cnpj":  "",
                      "object":  "AQUISICAO DE EQUIPAMENTOS 3 KITS “ACADEMIA AO AR LIVRE”, CONFORME CONVENIOS Nº 319/2021 (LOTE 1) E CONVENIO 199/2022 (LOTE 2), CELEBRADOS ENTRE O ESTADO DE SAO PAULO, POR INTERMEDIO DA SECRETARIA DE ESPORTES E O MUNICIPIO DE IGUAPE/SP, RECURSOS PROPRIOS (LOTE 3)",
                      "value":  "",
                      "term":  "",
                      "signatureDate":  "",
                      "legalBasis":  "",
                      "primaryOrganizationId":  "municipal-prefeitura",
                      "primaryOrganizationName":  "Prefeitura Municipal de Iguape",
                      "primaryOrganizationSphere":  "municipal",
                      "primaryOrganizationAreaId":  "governo",
                      "mentionedOrganizationIds":  [
                                                       "municipal-prefeitura",
                                                       "estadual-esportes"
                                                   ],
                      "mentionedOrganizationNames":  [
                                                         "Prefeitura Municipal de Iguape",
                                                         "Secretaria de Esportes"
                                                     ],
                      "excerpt":  "AVISO DE LICITACAO\n PREGAO PRESENCIAL\n\nEncontra-se ABERTO na Prefeitura Municipal de Iguape, situada na Avenida Adhemar de Barros, n.º 1.070, Bairro Porto do Ribeira, Iguape/SP, CEP\n11920-000, o PREGAO PRESENCIAL nº. 034/2023, do tipo MENOR VALOR GLOBAL POR LOTE, conforme especificacoes detalhadas no Edital.\nOBJETO: AQUISICAO DE EQUIPAMENTOS 3 KITS “ACADEMIA AO AR LIVRE”, CONFORME CONVENIOS Nº 319/2021 (LOTE 1) E CONVENIO\n199/2022 (LOTE 2), CELEBRADOS ENTRE O ESTADO DE SAO PAULO, POR INTERMEDIO DA SECRETARIA DE ESP",
                      "completeness":  "media",
                      "flags":  [

                                ]
                  },
                  {
                      "type":  "Aviso de Licitacao",
                      "actTitle":  "AVISO DE LICITACAO - PREGAO PRESENCIAL",
                      "recordClass":  "licitacao_ou_contratacao",
                      "recordClassLabel":  "Licitacao e contratacao",
                      "confidenceScore":  8,
                      "confidenceLabel":  "media",
                      "pageNumber":  4,
                      "contractNumber":  "",
                      "processNumber":  "035/2023",
                      "modality":  "PREGAO PRESENCIAL nº. 035/2023",
                      "contractor":  "",
                      "cnpj":  "",
                      "object":  "REGISTRO DE PRECOS PELO PERIODO DE 12 (DOZE) MESES, PARA AQUISICAO DE TUBOS DE CONCRETO ARMADO, PARA EXECUCAO DE SERVICOS DE MANEJO DE VALAS, TRANSPOSICOES DE CORPOS HIDRICOS E DRENAGEM PLUVIAL NO MUNICIPIO DE IGUAPE/SP",
                      "value":  "",
                      "term":  "",
                      "signatureDate":  "",
                      "legalBasis":  "",
                      "primaryOrganizationId":  "municipal-prefeitura",
                      "primaryOrganizationName":  "Prefeitura Municipal de Iguape",
                      "primaryOrganizationSphere":  "municipal",
                      "primaryOrganizationAreaId":  "governo",
                      "mentionedOrganizationIds":  [
                                                       "municipal-prefeitura"
                                                   ],
                      "mentionedOrganizationNames":  [
                                                         "Prefeitura Municipal de Iguape"
                                                     ],
                      "excerpt":  "AVISO DE LICITACAO\n PREGAO PRESENCIAL\n\nEncontra-se aberto na Prefeitura Municipal de Iguape, situada na Avenida Adhemar de Barros, n.º 1.070, Bairro Porto do Ribeira, Iguape/SP, CEP 11920-\n000 ,o PREGAO PRESENCIAL nº. 035/2023, do tipo MENOR PRECO POR ITEM, conforme especificacoes detalhadas no Edital.\n\nOBJETO: REGISTRO DE PRECOS PELO PERIODO DE 12 (DOZE) MESES, PARA AQUISICAO DE TUBOS DE CONCRETO ARMADO, PARA\nEXECUCAO DE SERVICOS DE MANEJO DE VALAS, TRANSPOSICOES DE CORPOS HIDRICOS E DRENAGEM PLUVIAL NO MUNICIPIO ",
                      "completeness":  "media",
                      "flags":  [

                                ]
                  }
              ]
}
