{
    "diaryId":  "687",
    "parserVersion":  "2026.04.01.11",
    "analyzedAt":  "2026-04-01T15:58:15",
    "sourcePdfUrl":  "https://www.iguape.sp.gov.br/uploads/8db6f58a447a9f8cf2e6e82884a809f9.pdf",
    "sourceLocalPdfRelative":  "storage/pdfs/2023/8db6f58a447a9f8cf2e6e82884a809f9.pdf",
    "keywords":  [
                     "contrato"
                 ],
    "analysisReason":  [
                           "keyword_map"
                       ],
    "summary":  {
                    "pageCount":  7,
                    "relevantPageCount":  4,
                    "blockCount":  9,
                    "itemCount":  4,
                    "totalValue":  "R$ 0,00"
                },
    "items":  [
                  {
                      "type":  "Gestao Contratual",
                      "actTitle":  "PORTARIA Nº 308",
                      "recordClass":  "gestao_contratual",
                      "recordClassLabel":  "Gestao do contrato",
                      "confidenceScore":  8,
                      "confidenceLabel":  "media",
                      "pageNumber":  1,
                      "contractNumber":  "178/2023",
                      "processNumber":  "",
                      "modality":  "",
                      "contractor":  "",
                      "cnpj":  "",
                      "object":  "empresa CIACAN ENGENHARIA EIRELI",
                      "value":  "",
                      "term":  "",
                      "signatureDate":  "",
                      "legalBasis":  "",
                      "primaryOrganizationId":  "municipal-infraestrutura-obras",
                      "primaryOrganizationName":  "Secretaria de Infraestrutura Urbana e Obras",
                      "primaryOrganizationSphere":  "municipal",
                      "primaryOrganizationAreaId":  "infraestrutura",
                      "mentionedOrganizationIds":  [
                                                       "municipal-prefeitura",
                                                       "municipal-gestao-planejamento",
                                                       "municipal-infraestrutura-obras"
                                                   ],
                      "mentionedOrganizationNames":  [
                                                         "Prefeitura Municipal de Iguape",
                                                         "Secretaria de Gestao e Planejamento",
                                                         "Secretaria de Infraestrutura Urbana e Obras"
                                                     ],
                      "excerpt":  "PORTARIA Nº 308\n DE 13 DE NOVEMBRO DE 2023\n\n DESIGNA GESTOR DO CONTRATO E DA OUTRAS PROVIDENCIAS.\n\n WILSON ALMEIDA LIMA, Prefeito Municipal de Iguape, Estado de Sao Paulo, no\nuso das atribuicoes que lhe sao conferidas pelo artigo 85, inciso IV, da Lei Organica do Municipio de Iguape, baixa a seguinte:\n\nArt. 1º - PORTARIA\nArt. 2º -\n Designa, Rafael de Barros Leite, Secretario Municipal de Infraestrutura e Obras, titular da Cedula de Identidade RG nº 26.166.016-0\n SSP/SP, inscrito no CPF/MF nº 256.609.068-85, para ex",
                      "completeness":  "baixa",
                      "flags":  [

                                ]
                  },
                  {
                      "type":  "Gestao Contratual",
                      "actTitle":  "PORTARIA Nº 310",
                      "recordClass":  "gestao_contratual",
                      "recordClassLabel":  "Gestao do contrato",
                      "confidenceScore":  8,
                      "confidenceLabel":  "media",
                      "pageNumber":  2,
                      "contractNumber":  "179/2023",
                      "processNumber":  "",
                      "modality":  "",
                      "contractor":  "",
                      "cnpj":  "",
                      "object":  "empresa CIACAN ENGENHARIA EIRELI",
                      "value":  "",
                      "term":  "",
                      "signatureDate":  "",
                      "legalBasis":  "",
                      "primaryOrganizationId":  "municipal-infraestrutura-obras",
                      "primaryOrganizationName":  "Secretaria de Infraestrutura Urbana e Obras",
                      "primaryOrganizationSphere":  "municipal",
                      "primaryOrganizationAreaId":  "infraestrutura",
                      "mentionedOrganizationIds":  [
                                                       "municipal-prefeitura",
                                                       "municipal-infraestrutura-obras"
                                                   ],
                      "mentionedOrganizationNames":  [
                                                         "Prefeitura Municipal de Iguape",
                                                         "Secretaria de Infraestrutura Urbana e Obras"
                                                     ],
                      "excerpt":  "PORTARIA Nº 310\n DE 13 DE NOVEMBRO DE 2023\n\n DESIGNA GESTOR DO CONTRATO E DA OUTRAS PROVIDENCIAS.\n\n WILSON ALMEIDA LIMA, Prefeito Municipal de Iguape, Estado de Sao Paulo, no\nuso das atribuicoes que lhe sao conferidas pelo artigo 85, inciso IV, da Lei Organica do Municipio de Iguape, baixa a seguinte:\n\n PORTARIA\n\nArt. 1º - Designa, Rafael de Barros Leite, Secretario Municipal de Infraestrutura e Obras, titular da Cedula de Identidade RG nº 26.166.016-0\nArt. 2º - SSP/SP, inscrito no CPF/MF nº 256.609.068-85, para ex",
                      "completeness":  "baixa",
                      "flags":  [

                                ]
                  },
                  {
                      "type":  "Gestao Contratual",
                      "actTitle":  "Portaria de gestao do contrato 180/2023",
                      "recordClass":  "gestao_contratual",
                      "recordClassLabel":  "Gestao do contrato",
                      "confidenceScore":  8,
                      "confidenceLabel":  "media",
                      "pageNumber":  3,
                      "contractNumber":  "180/2023",
                      "processNumber":  "",
                      "modality":  "",
                      "contractor":  "",
                      "cnpj":  "",
                      "object":  "empresa SAMUEL RIBEIRO - EPP",
                      "value":  "",
                      "term":  "",
                      "signatureDate":  "",
                      "legalBasis":  "",
                      "primaryOrganizationId":  "municipal-infraestrutura-obras",
                      "primaryOrganizationName":  "Secretaria de Infraestrutura Urbana e Obras",
                      "primaryOrganizationSphere":  "municipal",
                      "primaryOrganizationAreaId":  "infraestrutura",
                      "mentionedOrganizationIds":  [
                                                       "municipal-infraestrutura-obras",
                                                       "municipal-prefeitura"
                                                   ],
                      "mentionedOrganizationNames":  [
                                                         "Secretaria de Infraestrutura Urbana e Obras",
                                                         "Prefeitura Municipal de Iguape"
                                                     ],
                      "excerpt":  "Art. 1º - 3\nArt. 2º -\n Diario Oficial\n\n Iguape - SP\n\n ANO 03 – Nº 640 Quinta-feira, 16 de Novembro de 2023\n\n PORTARIA\n\n Designa, Rafael de Barros Leite, Secretario Municipal de Infraestrutura e Obras, titular da Cedula de Identidade RG nº 26.166.016-0\n SSP/SP, inscrito no CPF/MF nº 256.609.068-85, para exercer a funcao de Gestor do Contrato 180/2023, empresa SAMUEL RIBEIRO\n - EPP.\n Esta portaria entra em vigor na data de sua publicacao, revogadas as disposicoes em contrario.\n\n GABINETE DO PREFEITO\n\n WILSON ALMEIDA ",
                      "completeness":  "baixa",
                      "flags":  [

                                ]
                  },
                  {
                      "type":  "Gestao Contratual",
                      "actTitle":  "PORTARIA Nº 314",
                      "recordClass":  "gestao_contratual",
                      "recordClassLabel":  "Gestao do contrato",
                      "confidenceScore":  8,
                      "confidenceLabel":  "media",
                      "pageNumber":  3,
                      "contractNumber":  "181/2023",
                      "processNumber":  "",
                      "modality":  "",
                      "contractor":  "",
                      "cnpj":  "",
                      "object":  "empresa SAMUEL RIBEIRO - EPP",
                      "value":  "",
                      "term":  "",
                      "signatureDate":  "",
                      "legalBasis":  "",
                      "primaryOrganizationId":  "municipal-infraestrutura-obras",
                      "primaryOrganizationName":  "Secretaria de Infraestrutura Urbana e Obras",
                      "primaryOrganizationSphere":  "municipal",
                      "primaryOrganizationAreaId":  "infraestrutura",
                      "mentionedOrganizationIds":  [
                                                       "municipal-infraestrutura-obras",
                                                       "municipal-prefeitura"
                                                   ],
                      "mentionedOrganizationNames":  [
                                                         "Secretaria de Infraestrutura Urbana e Obras",
                                                         "Prefeitura Municipal de Iguape"
                                                     ],
                      "excerpt":  "PORTARIA Nº 314\n DE 13 DE NOVEMBRO DE 2023\n\n DESIGNA GESTOR DO CONTRATO E DA OUTRAS PROVIDENCIAS.\n\n WILSON ALMEIDA LIMA, Prefeito Municipal de Iguape, Estado de Sao Paulo, no\nuso das atribuicoes que lhe sao conferidas pelo artigo 85, inciso IV, da Lei Organica do Municipio de Iguape, baixa a seguinte:\n\n PORTARIA\n\nArt. 1º - Designa, Rafael de Barros Leite, Secretario Municipal de Infraestrutura e Obras, titular da Cedula de Identidade RG nº 26.166.016-0\nArt. 2º - SSP/SP, inscrito no CPF/MF nº 256.609.068-85, para ex",
                      "completeness":  "baixa",
                      "flags":  [

                                ]
                  }
              ]
}
